[
    {
        "pre": {
            "rewrite_acc": [
                0.4
            ],
            "locality": {
                "Relation_Specificity_output": [
                    [
                        220,
                        16,
                        20,
                        20,
                        15,
                        42242,
                        4110
                    ]
                ]
            },
            "portability": {
                "Subject_Aliasing_acc": [
                    0.4
                ],
                "Logical_Generalization_acc": [
                    0.14285714285714285
                ]
            },
            "fluency": {
                "ngram_entropy": 6.143326244768824
            }
        }
    },
    {
        "pre": {
            "rewrite_acc": [
                0.6
            ],
            "locality": {
                "Relation_Specificity_output": [
                    [
                        279,
                        16,
                        24,
                        22,
                        19,
                        33311,
                        11461,
                        76,
                        7306,
                        47754,
                        1365,
                        3198,
                        594,
                        39296
                    ]
                ]
            },
            "portability": {
                "Subject_Aliasing_acc": [
                    0.4
                ],
                "reasoning_acc": [
                    0.0
                ],
                "Logical_Generalization_acc": [
                    0.0
                ]
            },
            "fluency": {
                "ngram_entropy": 6.301051200148931
            }
        }
    },
    {
        "pre": {
            "rewrite_acc": [
                0.5714285714285714
            ],
            "locality": {
                "Relation_Specificity_output": [
                    [
                        198
                    ]
                ]
            },
            "portability": {
                "Subject_Aliasing_acc": [
                    0.5714285714285714
                ],
                "Logical_Generalization_acc": [
                    0.3333333333333333
                ]
            },
            "fluency": {
                "ngram_entropy": 4.8410956099302105
            }
        }
    },
    {
        "pre": {
            "rewrite_acc": [
                0.5
            ],
            "locality": {
                "Relation_Specificity_output": [
                    [
                        279,
                        17,
                        15,
                        17,
                        21,
                        14811,
                        11461,
                        76,
                        7306,
                        47754,
                        1365,
                        2953,
                        594,
                        39296
                    ]
                ]
            },
            "portability": {
                "Subject_Aliasing_acc": [
                    0.5
                ],
                "reasoning_acc": [
                    0.0
                ],
                "Logical_Generalization_acc": [
                    0.0
                ]
            },
            "fluency": {
                "ngram_entropy": 6.107935370380366
            }
        }
    },
    {
        "pre": {
            "rewrite_acc": [
                0.0
            ],
            "locality": {
                "Relation_Specificity_output": [
                    [
                        8593
                    ]
                ],
                "Forgetfulness_output": [
                    [
                        510
                    ]
                ]
            },
            "portability": {
                "Subject_Aliasing_acc": [
                    0.0
                ],
                "reasoning_acc": [
                    0.6666666666666666
                ]
            },
            "fluency": {
                "ngram_entropy": 6.020770436171857
            }
        }
    },
    {
        "pre": {
            "rewrite_acc": [
                0.5
            ],
            "locality": {
                "Relation_Specificity_output": [
                    [
                        8593
                    ]
                ],
                "Forgetfulness_output": [
                    [
                        264,
                        12644,
                        2781
                    ]
                ]
            },
            "portability": {
                "Subject_Aliasing_acc": [
                    0.5
                ]
            },
            "fluency": {
                "ngram_entropy": 5.88922306582088
            }
        }
    },
    {
        "pre": {
            "rewrite_acc": [
                0.625
            ],
            "locality": {
                "Relation_Specificity_output": [
                    [
                        8593
                    ]
                ],
                "Forgetfulness_output": [
                    [
                        510,
                        4180,
                        13,
                        5159
                    ]
                ]
            },
            "portability": {
                "Subject_Aliasing_acc": [
                    0.75
                ],
                "reasoning_acc": [
                    0.5
                ]
            },
            "fluency": {
                "ngram_entropy": 6.054820012149859
            }
        }
    },
    {
        "pre": {
            "rewrite_acc": [
                0.2
            ],
            "locality": {
                "Relation_Specificity_output": [
                    [
                        198,
                        13
                    ]
                ],
                "Forgetfulness_output": [
                    [
                        2661,
                        13
                    ]
                ]
            },
            "portability": {
                "Subject_Aliasing_acc": [
                    0.2
                ]
            },
            "fluency": {
                "ngram_entropy": 5.834675168419892
            }
        }
    },
    {
        "pre": {
            "rewrite_acc": [
                0.5
            ],
            "locality": {
                "Relation_Specificity_output": [
                    [
                        8778
                    ]
                ]
            },
            "portability": {},
            "fluency": {
                "ngram_entropy": 6.096517382316719
            }
        }
    },
    {
        "pre": {
            "rewrite_acc": [
                0.0
            ],
            "locality": {
                "Relation_Specificity_output": [
                    [
                        8593
                    ]
                ],
                "Forgetfulness_output": [
                    [
                        510
                    ]
                ]
            },
            "portability": {
                "Subject_Aliasing_acc": [
                    0.0
                ],
                "reasoning_acc": [
                    0.0
                ]
            },
            "fluency": {
                "ngram_entropy": 6.305702406620304
            }
        }
    },
    {
        "pre": {
            "rewrite_acc": [
                0.0
            ],
            "locality": {
                "Forgetfulness_output": [
                    [
                        510,
                        16550,
                        13,
                        23905
                    ]
                ]
            },
            "portability": {
                "reasoning_acc": [
                    0.0
                ]
            },
            "fluency": {
                "ngram_entropy": 5.958692044120584
            }
        }
    },
    {
        "pre": {
            "rewrite_acc": [
                0.3333333333333333
            ],
            "locality": {
                "Relation_Specificity_output": [
                    [
                        9788,
                        76018,
                        578,
                        13,
                        34507,
                        352
                    ]
                ]
            },
            "portability": {
                "Subject_Aliasing_acc": [
                    0.3333333333333333
                ],
                "reasoning_acc": [
                    0.0
                ],
                "Logical_Generalization_acc": [
                    0.14285714285714285
                ]
            },
            "fluency": {
                "ngram_entropy": 5.9558533735735875
            }
        }
    },
    {
        "pre": {
            "rewrite_acc": [
                0.0
            ],
            "locality": {
                "Forgetfulness_output": [
                    [
                        23654
                    ]
                ]
            },
            "portability": {
                "Subject_Aliasing_acc": [
                    0.5
                ]
            },
            "fluency": {
                "ngram_entropy": 6.162334900344353
            }
        }
    },
    {
        "pre": {
            "rewrite_acc": [
                0.2222222222222222
            ],
            "locality": {
                "Relation_Specificity_output": [
                    [
                        422
                    ]
                ]
            },
            "portability": {
                "Subject_Aliasing_acc": [
                    0.4444444444444444
                ],
                "Logical_Generalization_acc": [
                    0.0
                ]
            },
            "fluency": {
                "ngram_entropy": 5.510352651640168
            }
        }
    },
    {
        "pre": {
            "rewrite_acc": [
                0.42105263157894735
            ],
            "locality": {
                "Relation_Specificity_output": [
                    [
                        264,
                        3004,
                        11,
                        55923,
                        78728,
                        76
                    ]
                ]
            },
            "portability": {
                "Subject_Aliasing_acc": [
                    0.47368421052631576
                ],
                "Logical_Generalization_acc": [
                    0.0
                ]
            },
            "fluency": {
                "ngram_entropy": 6.401747220909094
            }
        }
    },
    {
        "pre": {
            "rewrite_acc": [
                0.6666666666666666
            ],
            "locality": {
                "Relation_Specificity_output": [
                    [
                        8778
                    ]
                ],
                "Forgetfulness_output": [
                    [
                        510,
                        36926,
                        3234,
                        3822
                    ]
                ]
            },
            "portability": {
                "Subject_Aliasing_acc": [
                    0.5555555555555556
                ]
            },
            "fluency": {
                "ngram_entropy": 6.197660808179964
            }
        }
    },
    {
        "pre": {
            "rewrite_acc": [
                0.0
            ],
            "locality": {
                "Forgetfulness_output": [
                    [
                        5267,
                        19059,
                        6040,
                        12800,
                        2780,
                        386,
                        1195
                    ]
                ]
            },
            "portability": {
                "reasoning_acc": [
                    0.0
                ]
            },
            "fluency": {
                "ngram_entropy": 5.831212723640165
            }
        }
    },
    {
        "pre": {
            "rewrite_acc": [
                0.5
            ],
            "locality": {
                "Relation_Specificity_output": [
                    [
                        510,
                        98012,
                        27942,
                        13,
                        355
                    ]
                ],
                "Forgetfulness_output": [
                    [
                        510,
                        315,
                        17520,
                        7217,
                        315,
                        95814
                    ]
                ]
            },
            "portability": {
                "Subject_Aliasing_acc": [
                    0.5
                ]
            },
            "fluency": {
                "ngram_entropy": 5.802121128219991
            }
        }
    },
    {
        "pre": {
            "rewrite_acc": [
                0.3333333333333333
            ],
            "locality": {
                "Relation_Specificity_output": [
                    [
                        29494,
                        408,
                        529,
                        27897,
                        648,
                        517,
                        13,
                        38569,
                        261
                    ]
                ]
            },
            "portability": {
                "Subject_Aliasing_acc": [
                    0.3333333333333333
                ]
            },
            "fluency": {
                "ngram_entropy": 6.249780993558274
            }
        }
    },
    {
        "pre": {
            "rewrite_acc": [
                0.0
            ],
            "locality": {
                "Relation_Specificity_output": [
                    [
                        8778
                    ]
                ],
                "Forgetfulness_output": [
                    [
                        264,
                        27086
                    ]
                ]
            },
            "portability": {
                "Subject_Aliasing_acc": [
                    0.0
                ]
            },
            "fluency": {
                "ngram_entropy": 6.35782605588334
            }
        }
    },
    {
        "pre": {
            "rewrite_acc": [
                0.0
            ],
            "locality": {
                "Relation_Specificity_output": [
                    [
                        2661,
                        3822
                    ]
                ],
                "Forgetfulness_output": [
                    [
                        264
                    ]
                ]
            },
            "portability": {
                "Subject_Aliasing_acc": [
                    0.0
                ],
                "reasoning_acc": [
                    0.0
                ]
            },
            "fluency": {
                "ngram_entropy": 6.057708790394003
            }
        }
    },
    {
        "pre": {
            "rewrite_acc": [
                0.6666666666666666
            ],
            "locality": {
                "Relation_Specificity_output": [
                    [
                        9788,
                        3757,
                        444,
                        769,
                        13709,
                        13,
                        220,
                        16,
                        339,
                        52907,
                        295
                    ]
                ]
            },
            "portability": {
                "Subject_Aliasing_acc": [
                    0.6666666666666666
                ],
                "reasoning_acc": [
                    0.7142857142857143
                ],
                "Logical_Generalization_acc": [
                    0.09090909090909091
                ]
            },
            "fluency": {
                "ngram_entropy": 6.293194186173574
            }
        }
    },
    {
        "pre": {
            "rewrite_acc": [
                0.0
            ],
            "locality": {
                "Relation_Specificity_output": [
                    [
                        9788,
                        35747,
                        64
                    ]
                ]
            },
            "portability": {
                "Subject_Aliasing_acc": [
                    0.0
                ]
            },
            "fluency": {
                "ngram_entropy": 6.157353600973234
            }
        }
    },
    {
        "pre": {
            "rewrite_acc": [
                0.25
            ],
            "locality": {
                "Relation_Specificity_output": [
                    [
                        8593
                    ]
                ],
                "Forgetfulness_output": [
                    [
                        264,
                        13
                    ]
                ]
            },
            "portability": {
                "Subject_Aliasing_acc": [
                    0.25
                ]
            },
            "fluency": {
                "ngram_entropy": 6.200863619021451
            }
        }
    },
    {
        "pre": {
            "rewrite_acc": [
                0.0
            ],
            "locality": {
                "Relation_Specificity_output": [
                    [
                        9788,
                        315,
                        49795,
                        8319
                    ]
                ],
                "Forgetfulness_output": [
                    [
                        264
                    ]
                ]
            },
            "portability": {
                "Subject_Aliasing_acc": [
                    0.0
                ]
            },
            "fluency": {
                "ngram_entropy": 5.715587462952038
            }
        }
    },
    {
        "pre": {
            "rewrite_acc": [
                0.3333333333333333
            ],
            "locality": {
                "Relation_Specificity_output": [
                    [
                        264
                    ]
                ],
                "Forgetfulness_output": [
                    [
                        510,
                        16209,
                        8319,
                        9074
                    ]
                ]
            },
            "portability": {
                "Subject_Aliasing_acc": [
                    0.3333333333333333
                ],
                "reasoning_acc": [
                    0.3333333333333333
                ]
            },
            "fluency": {
                "ngram_entropy": 6.388460631896906
            }
        }
    },
    {
        "pre": {
            "rewrite_acc": [
                0.0
            ],
            "locality": {
                "Relation_Specificity_output": [
                    [
                        279,
                        12402
                    ]
                ]
            },
            "portability": {
                "Subject_Aliasing_acc": [
                    0.0
                ],
                "Logical_Generalization_acc": [
                    0.0
                ]
            },
            "fluency": {
                "ngram_entropy": 6.273152180456411
            }
        }
    },
    {
        "pre": {
            "rewrite_acc": [
                0.2
            ],
            "locality": {
                "Relation_Specificity_output": [
                    [
                        510,
                        8095,
                        5016,
                        273,
                        1038,
                        1194
                    ]
                ],
                "Forgetfulness_output": [
                    [
                        510,
                        3441,
                        13,
                        273,
                        1038,
                        1194,
                        859,
                        1953
                    ]
                ]
            },
            "portability": {
                "Subject_Aliasing_acc": [
                    0.2
                ],
                "reasoning_acc": [
                    0.2
                ]
            },
            "fluency": {
                "ngram_entropy": 5.380665124833486
            }
        }
    },
    {
        "pre": {
            "rewrite_acc": [
                1.0
            ],
            "locality": {
                "Relation_Specificity_output": [
                    [
                        9788,
                        12611,
                        12556
                    ]
                ]
            },
            "portability": {
                "Subject_Aliasing_acc": [
                    1.0
                ]
            },
            "fluency": {
                "ngram_entropy": 6.3009440990959
            }
        }
    },
    {
        "pre": {
            "rewrite_acc": [
                0.0
            ],
            "locality": {
                "Relation_Specificity_output": [
                    [
                        8778
                    ]
                ],
                "Forgetfulness_output": [
                    [
                        264
                    ]
                ]
            },
            "portability": {
                "Subject_Aliasing_acc": [
                    0.0
                ]
            },
            "fluency": {
                "ngram_entropy": 6.162739196433512
            }
        }
    },
    {
        "pre": {
            "rewrite_acc": [
                0.0
            ],
            "locality": {
                "Relation_Specificity_output": [
                    [
                        28638
                    ]
                ],
                "Forgetfulness_output": [
                    [
                        5267,
                        6215,
                        7019,
                        21490
                    ]
                ]
            },
            "portability": {
                "Subject_Aliasing_acc": [
                    0.0
                ]
            },
            "fluency": {
                "ngram_entropy": 5.91511321850004
            }
        }
    },
    {
        "pre": {
            "rewrite_acc": [
                0.0
            ],
            "locality": {
                "Relation_Specificity_output": [
                    [
                        198,
                        3234,
                        3822
                    ]
                ],
                "Forgetfulness_output": [
                    [
                        510,
                        315,
                        279,
                        11,
                        5836,
                        11902
                    ]
                ]
            },
            "portability": {
                "Subject_Aliasing_acc": [
                    0.0
                ],
                "reasoning_acc": [
                    0.3333333333333333
                ]
            },
            "fluency": {
                "ngram_entropy": 6.054313165593749
            }
        }
    },
    {
        "pre": {
            "rewrite_acc": [
                0.3333333333333333
            ],
            "locality": {
                "Relation_Specificity_output": [
                    [
                        264
                    ]
                ]
            },
            "portability": {
                "Subject_Aliasing_acc": [
                    0.3333333333333333
                ]
            },
            "fluency": {
                "ngram_entropy": 6.176773416102446
            }
        }
    },
    {
        "pre": {
            "rewrite_acc": [
                0.3333333333333333
            ],
            "locality": {
                "Relation_Specificity_output": [
                    [
                        8593
                    ]
                ]
            },
            "portability": {
                "Subject_Aliasing_acc": [
                    0.3333333333333333
                ],
                "reasoning_acc": [
                    0.25
                ],
                "Logical_Generalization_acc": [
                    0.0
                ]
            },
            "fluency": {
                "ngram_entropy": 5.585725878721698
            }
        }
    },
    {
        "pre": {
            "rewrite_acc": [
                0.5
            ],
            "locality": {
                "Relation_Specificity_output": [
                    [
                        8593
                    ]
                ],
                "Forgetfulness_output": [
                    [
                        510,
                        16328,
                        17411
                    ]
                ]
            },
            "portability": {
                "Subject_Aliasing_acc": [
                    0.5
                ]
            },
            "fluency": {
                "ngram_entropy": 6.218116811992516
            }
        }
    },
    {
        "pre": {
            "rewrite_acc": [
                0.5
            ],
            "locality": {
                "Relation_Specificity_output": [
                    [
                        198,
                        3822
                    ]
                ]
            },
            "portability": {
                "Subject_Aliasing_acc": [
                    0.5
                ],
                "reasoning_acc": [
                    0.5
                ]
            },
            "fluency": {
                "ngram_entropy": 6.252118279971807
            }
        }
    },
    {
        "pre": {
            "rewrite_acc": [
                0.0
            ],
            "locality": {
                "Relation_Specificity_output": [
                    [
                        8593
                    ]
                ],
                "Forgetfulness_output": [
                    [
                        264
                    ]
                ]
            },
            "portability": {
                "Subject_Aliasing_acc": [
                    0.0
                ]
            },
            "fluency": {
                "ngram_entropy": 5.995466560149537
            }
        }
    },
    {
        "pre": {
            "rewrite_acc": [
                0.3333333333333333
            ],
            "locality": {
                "Relation_Specificity_output": [
                    [
                        4509,
                        610,
                        276,
                        25257,
                        220,
                        16,
                        24,
                        24,
                        17,
                        14,
                        16,
                        24,
                        24,
                        18,
                        1365,
                        3665,
                        220,
                        17
                    ]
                ]
            },
            "portability": {
                "Subject_Aliasing_acc": [
                    0.0
                ]
            },
            "fluency": {
                "ngram_entropy": 5.759058501778716
            }
        }
    },
    {
        "pre": {
            "rewrite_acc": [
                0.5714285714285714
            ],
            "locality": {
                "Forgetfulness_output": [
                    [
                        1304,
                        619,
                        13
                    ]
                ]
            },
            "portability": {
                "Subject_Aliasing_acc": [
                    0.5714285714285714
                ],
                "reasoning_acc": [
                    0.0
                ]
            },
            "fluency": {
                "ngram_entropy": 6.144557122566575
            }
        }
    },
    {
        "pre": {
            "rewrite_acc": [
                0.0
            ],
            "locality": {
                "Relation_Specificity_output": [
                    [
                        9788,
                        1315,
                        18307
                    ]
                ]
            },
            "portability": {
                "Subject_Aliasing_acc": [
                    0.0
                ]
            },
            "fluency": {
                "ngram_entropy": 6.331252632804808
            }
        }
    },
    {
        "pre": {
            "rewrite_acc": [
                0.2857142857142857
            ],
            "locality": {
                "Relation_Specificity_output": [
                    [
                        220,
                        343,
                        11,
                        11,
                        87864,
                        42648,
                        320,
                        16,
                        8
                    ]
                ]
            },
            "portability": {
                "Subject_Aliasing_acc": [
                    0.35714285714285715
                ],
                "Logical_Generalization_acc": [
                    0.0
                ]
            },
            "fluency": {
                "ngram_entropy": 6.347440402233975
            }
        }
    },
    {
        "pre": {
            "rewrite_acc": [
                0.0
            ],
            "locality": {
                "Forgetfulness_output": [
                    [
                        264
                    ]
                ]
            },
            "portability": {
                "Subject_Aliasing_acc": [
                    0.0
                ]
            },
            "fluency": {
                "ngram_entropy": 6.004605429955631
            }
        }
    },
    {
        "pre": {
            "rewrite_acc": [
                0.3125
            ],
            "locality": {
                "Relation_Specificity_output": [
                    [
                        279,
                        51903,
                        518,
                        279,
                        220,
                        16,
                        24,
                        24,
                        17,
                        18836,
                        31963,
                        1365,
                        2953,
                        594,
                        220,
                        21,
                        22,
                        20972
                    ]
                ]
            },
            "portability": {
                "Subject_Aliasing_acc": [
                    0.3125
                ],
                "Logical_Generalization_acc": [
                    0.6
                ]
            },
            "fluency": {
                "ngram_entropy": 5.898510395500798
            }
        }
    }
]